relseg/__init__.py
relseg/__main__.py
relseg/ctc.py
relseg/custom_model_loader.py
relseg/lrp.py
relseg/lrp_rules.py
relseg/lxt_adjustments.py
relseg/lxt_composites.py
relseg/main_lrp_entry.py
relseg/relevance_plotting.py
relseg/stitching.py
relseg/writer.py
relseg/transformer/RMSNorm.py
relseg/transformer/RoPE.py
relseg/transformer/__init__.py
relseg/transformer/model_lxt.py
relseg/transformer/model_modified_unused.py
relseg/transformer/nn.py
relseg-0.1.0.dist-info/LICENCE.txt
relseg-0.1.0.dist-info/METADATA
relseg-0.1.0.dist-info/WHEEL
relseg-0.1.0.dist-info/entry_points.txt
relseg-0.1.0.dist-info/top_level.txt
relseg-0.1.0.dist-info/RECORD
