Metadata-Version: 2.2
Name: relseg
Version: 0.1.0
Author: LKoehler
Requires-Python: ==3.10
License-File: LICENCE.txt
Requires-Dist: edlib
Requires-Dist: fast-ctc-decode
Requires-Dist: mappy
Requires-Dist: networkx
Requires-Dist: numpy<2
Requires-Dist: pandas<3
Requires-Dist: parasail
Requires-Dist: pod5
Requires-Dist: pysam
Requires-Dist: python-dateutil
Requires-Dist: requests
Requires-Dist: toml
Requires-Dist: tqdm
Requires-Dist: wheel
Requires-Dist: torch==2.1.2
Requires-Dist: ont-bonito
Requires-Dist: ont-fast5-api
Requires-Dist: ont-koi
Requires-Dist: ont-remora
Requires-Dist: zennit==0.5.1
Requires-Dist: lxt==0.6.1
Dynamic: author
Dynamic: description
Dynamic: description-content-type
Dynamic: requires-dist
Dynamic: requires-python
